pyqs/__init__.py
pyqs/decorator.py
pyqs/events.py
pyqs/main.py
pyqs/utils.py
pyqs/worker.py
pyqs-1.0.1.dist-info/LICENSE.md
pyqs-1.0.1.dist-info/METADATA
pyqs-1.0.1.dist-info/WHEEL
pyqs-1.0.1.dist-info/entry_points.txt
pyqs-1.0.1.dist-info/top_level.txt
pyqs-1.0.1.dist-info/RECORD
