Metadata-Version: 2.1
Name: pyqs
Version: 1.0.1
Summary: A simple task-queue for SQS.
Home-page: https://github.com/spulec/pyqs
Author: Steve Pulec
Author-email: spulec@gmail.com
License: UNKNOWN
Platform: UNKNOWN
License-File: LICENSE.md
Requires-Dist: boto3 (>=1.7.0)
